src/macPipe.sv
module macPipe #(
	parameter int WIDTH = 8
)(
	input logic [WIDTH-1:0] A, B, 
	input logic rst, acc, valid_in, clk,
	output logic [WIDTH*3-1:0] result, 
	output logic valid_out
);
	reg [WIDTH*2-1:0] mul_reg;
	reg acc_reg;
	reg valid;

	always_ff @(posedge clk) begin
		acc_reg <= acc;
		valid <= valid_in;

		case ({rst, valid_in})
			2'b10: begin
				mul_reg <= 0;
				valid <= 0;
				acc_reg <= 0;
			end
			2'b11: begin
				mul_reg <= 0;
				valid <= 0;
				acc_reg <= 0;
			end
			2'b00: mul_reg <= mul_reg;
			2'b01: mul_reg <= (WIDTH*2)'(A) * (WIDTH*2)'(B);
		endcase
	end

	always_ff @(posedge clk) begin
		valid_out <= valid;

		case ({rst, valid, acc_reg})
			3'b101: begin
				result <= 0;
				valid_out <= 0;
			end
			3'b111: begin
				result <= 0;
				valid_out <= 0;
			end
			3'b100: begin
				result <= 0;
				valid_out <= 0;
			end
			3'b110: begin
				result <= 0;
				valid_out <= 0;
			end
			3'b000: result <= result;
			3'b001: result <= result;
			3'b010: result <= {{(WIDTH){1'b0}}, mul_reg};
			3'b011: result <= result + {{(WIDTH){1'b0}}, mul_reg};
		endcase		
	end
endmodule

src/dump.vcd
$version Generated by VerilatedVcd $end
$timescale 1ps $end
 $scope module TOP $end
  $var wire 8 & A [7:0] $end
  $var wire 8 ' B [7:0] $end
  $var wire 1 ( rst $end
  $var wire 1 ) acc $end
  $var wire 1 * valid_in $end
  $var wire 1 + clk $end
  $var wire 24 , result [23:0] $end
  $var wire 1 - valid_out $end
  $scope module macPipe $end
   $var wire 32 . WIDTH [31:0] $end
   $var wire 8 & A [7:0] $end
   $var wire 8 ' B [7:0] $end
   $var wire 1 ( rst $end
   $var wire 1 ) acc $end
   $var wire 1 * valid_in $end
   $var wire 1 + clk $end
   $var wire 24 , result [23:0] $end
   $var wire 1 - valid_out $end
   $var wire 16 # mul_reg [15:0] $end
   $var wire 1 $ acc_reg $end
   $var wire 1 % valid $end
  $upscope $end
 $upscope $end
$enddefinitions $end


#0
b0000000000000000 #
0$
0%
b00000000 &
b00000000 '
1(
1)
0*
0+
b000000000000000000000000 ,
0-
b00000000000000000000000000001000 .
#10
1+
#20
0(
1*
0+
#30
b0001001001011100 #
1$
1%
b01100100 &
b00101111 '
1+
#35
0+
#40
b0000110000110000 #
b00011010 &
b01111000 '
1+
b000000000001001001011100 ,
1-
#45
0+
#50
b0010100011111100 #
b11110100 &
b00101011 '
1+
b000000000001111010001100 ,
#55
0+
#60
b0000100101110010 #
b00111110 &
b00100111 '
1+
b000000000100011110001000 ,
#65
0+
#70
b0001001000001100 #
b00100001 &
b10001100 '
1+
b000000000101000011111010 ,
#75
0+
#80
b0010010000000000 #
b10010000 &
b01000000 '
1+
b000000000110001100000110 ,
#85
0+
#90
b0101101100010100 #
b01110100 &
b11001001 '
1+
b000000001000011100000110 ,
#95
0+
#100
b0011101101010000 #
b10010010 &
b01101000 '
1+
b000000001110001000011010 ,
#105
0+
#110
b0100010000100000 #
b11011010 &
b01010000 '
1+
b000000010001110101101010 ,
#115
0+
#120
b1001001101101100 #
b11001100 &
b10111001 '
1+
b000000010110000110001010 ,
#125
0+
#130
b0101100001100000 #
b11001010 &
b01110000 '
1+
b000000011111010011110110 ,
#135
0+
#140
b0000001111111110 #
b00000111 &
b10010010 '
1+
b000000100100110101010110 ,
#145
0+
#150
b0110110110000000 #
b10010010 &
b11000000 '
1+
b000000100101000101010100 ,
#155
0+
#160
b0000111001110000 #
b00011100 &
b10000100 '
1+
b000000101011111011010100 ,
#165
0+
#170
b0001001100101001 #
b01101101 &
b00101101 '
1+
b000000101100110101000100 ,
#175
0+
#180
b1000101110011011 #
b10101011 &
b11010001 '
1+
b000000101110000001101101 ,
#185
0+
#190
b0100011100101000 #
b01011100 &
b11000110 '
1+
b000000110110110000001000 ,
#195
0+
#200
b0001011100100000 #
b01001010 &
b01010000 '
1+
b000000111011001100110000 ,
#205
0+
#210
b1000000000001000 #
b11110001 &
b10001000 '
1+
b000000111100101001010000 ,
#215
0+
#220
b0000100001011110 #
b01110111 &
b00010010 '
1+
b000001000100101001011000 ,
#225
0+
#230
b0000000010100000 #
b00010100 &
b00001000 '
1+
b000001000101001010110110 ,
#235
0+
#240
b0010110000011000 #
b01010011 &
b10001000 '
1+
b000001000101001101010110 ,
#245
0+
#250
b1011101011110101 #
b11010001 &
b11100101 '
1+
b000001000111111101101110 ,
#255
0+
#260
b1010000111101100 #
b11110001 &
b10101100 '
1+
b000001010011101001100011 ,
#265
0+
#270
b0010011111011110 #
b00110110 &
b10111101 '
1+
b000001011101110001001111 ,
#275
0+
#280
b0000000000000000 #
b01100101 &
b00000000 '
1+
b000001100000010000101101 ,
#285
0+
#290
b0001001101101000 #
b00101110 &
b01101100 '
1+
#295
0+
#300
b0110110110000000 #
b10010010 &
b11000000 '
1+
b000001100001011110010101 ,
#305
0+
#310
b0001110111101000 #
b00101100 &
b10101110 '
1+
b000001101000010100010101 ,
#315
0+
#320
b0010100010100100 #
b01000100 &
b10011001 '
1+
b000001101010001011111101 ,
#325
0+
#330
b1100110101010000 #
b11011011 &
b11110000 '
1+
b000001101100101110100001 ,
#335
0+
#340
b0001011011111101 #
b01101011 &
b00110111 '
1+
b000001111001100011110001 ,
#345
0+
#350
b1000000010101110 #
b10110110 &
b10110101 '
1+
b000001111010111111101110 ,
#355
0+
#360
b0101100010111000 #
b10001000 &
b10100111 '
1+
b000010000011000010011100 ,
#365
0+
#370
b0011110011000011 #
b00111101 &
b11111111 '
1+
b000010001000100101010100 ,
#375
0+
#380
b0011101011011010 #
b10111010 &
b01010001 '
1+
b000010001100011000010111 ,
#385
0+
#390
b0000000001011011 #
b00000111 &
b00001101 '
1+
b000010010000000011110001 ,
#395
0+
#400
b1011100011001010 #
b11011010 &
b11011001 '
1+
b000010010000000101001100 ,
#405
0+
#410
b1011111111100110 #
b11110010 &
b11001011 '
1+
b000010011011101000010110 ,
#415
0+
#420
b0001010011001000 #
b10000101 &
b00101000 '
1+
b000010100111100111111100 ,
#425
0+
#430
b0111110001010000 #
b10001000 &
b11101010 '
1+
b000010101000111011000100 ,
#435
0+
#440
b0001110001110000 #
b00101000 &
b10110110 '
1+
b000010110000101100010100 ,
#445
0+
#450
b0011111001111100 #
b01010110 &
b10111010 '
1+
b000010110010011110000100 ,
#455
0+
#460
b0011110011100101 #
b01110111 &
b10000011 '
1+
b000010110110011000000000 ,
#465
0+
#470
b0100110010110011 #
b01101001 &
b10111011 '
1+
b000010111010001011100101 ,
#475
0+
#480
b0000011101110000 #
b00011100 &
b01000100 '
1+
b000010111110111110011000 ,
#485
0+
#490
b0101101000101101 #
b10101011 &
b10000111 '
1+
b000010111111011100001000 ,
#495
0+
#500
b0010111011111100 #
b01111100 &
b01100001 '
1+
b000011000101000100110101 ,
#505
0+
#510
b0000000011110000 #
b00111100 &
b00000100 '
1+
b000011001000000000110001 ,
#515
0+
#520
b0000010001000001 #
b00001001 &
b01111001 '
1+
b000011001000000100100001 ,
#525
0+
#530
b0000001001001001 #
b00000011 &
b11000011 '
1+
b000011001000010101100010 ,
#535
0+
#540
b0000100010111001 #
b11001011 &
b00001011 '
1+
b000011001000011110101011 ,
#545
0+
#550
b1000011000010000 #
b11010000 &
b10100101 '
1+
b000011001001000001100100 ,
#555
0+
#560
b1010110011001000 #
b11100100 &
b11000010 '
1+
b000011010001011001110100 ,
#565
0+
#570
b0010110111110000 #
b01110000 &
b01101001 '
1+
b000011011100001100111100 ,
#575
0+
#580
b1110001110101000 #
b11101011 &
b11111000 '
1+
b000011011111000100101100 ,
#585
0+
#590
b0000011000101001 #
b01010011 &
b00010011 '
1+
b000011101101010011010100 ,
#595
0+
#600
b0111001110000111 #
b10101111 &
b10101001 '
1+
b000011101101101011111101 ,
#605
0+
#610
b0001111010010100 #
b11001110 &
b00100110 '
1+
b000011110100111010000100 ,
#615
0+
#620
b0000100101110100 #
b00101100 &
b00110111 '
1+
b000011110110110100011000 ,
#625
0+
#630
b0100000000101001 #
b11100001 &
b01001001 '
1+
b000011110111011010001100 ,
#635
0+
#640
b0100001110111111 #
b01111011 &
b10001101 '
1+
b000011111011011010110101 ,
#645
0+
#650
b1100100010110000 #
b11010000 &
b11110111 '
1+
b000011111111101001110100 ,
#655
0+
#660
b0000110000010110 #
b11101110 &
b00001101 '
1+
b000100001100001100100100 ,
#665
0+
#670
b1111001000101101 #
b11111011 &
b11110111 '
1+
b000100001100111100111010 ,
#675
0+
#680
b1000010101111010 #
b10000110 &
b11111111 '
1+
b000100011100000101100111 ,
#685
0+
#690
b0011101011011010 #
b10111010 &
b01010001 '
1+
b000100100100011011100001 ,
#695
0+
#700
b0000010101100100 #
b00001010 &
b10001010 '
1+
b000100101000000110111011 ,
#705
0+
#710
b1110010010110100 #
b11110110 &
b11101110 '
1+
b000100101000011100011111 ,
#715
0+
#720
b0001111010101110 #
b01001101 &
b01100110 '
1+
b000100110110101111010011 ,
#725
0+
#730
b0001001100001000 #
b01010111 &
b00111000 '
1+
b000100111000101010000001 ,
#735
0+
#740
b0011111100010110 #
b01011111 &
b10101010 '
1+
b000100111001110110001001 ,
#745
0+
#750
b0000010000011010 #
b01001011 &
b00001110 '
1+
b000100111101110010011111 ,
#755
0+
#760
b0000100000011011 #
b01010011 &
b00011001 '
1+
b000100111110000010111001 ,
#765
0+
#770
b0001101000000000 #
b00110100 &
b10000000 '
1+
b000100111110100011010100 ,
#775
0+
#780
b0000011010010000 #
b01010000 &
b00010101 '
1+
b000101000000001011010100 ,
#785
0+
#790
b1010000000101100 #
b11001001 &
b11001100 '
1+
b000101000000100101100100 ,
#795
0+
#800
b0110000011010010 #
b10100010 &
b10011001 '
1+
b000101001010100110010000 ,
#805
0+
#810
b0110111001110011 #
b11000011 &
b10010001 '
1+
b000101010000101001100010 ,
#815
0+
#820
b0111101111011010 #
b10100110 &
b10111111 '
1+
b000101010111100011010101 ,
#825
0+
#830
b0001011111101000 #
b10001000 &
b00101101 '
1+
b000101011111010010101111 ,
#835
0+
#840
b0011000110111010 #
b10111110 &
b01000011 '
1+
b000101100000110010010111 ,
#845
0+
#850
b0110001001110000 #
b01111110 &
b11001000 '
1+
b000101100011111001010001 ,
#855
0+
#860
b0101110110110001 #
b11001101 &
b01110101 '
1+
b000101101010000011000001 ,
#865
0+
#870
b0001001001111100 #
b10110110 &
b00011010 '
1+
b000101101111111001110010 ,
#875
0+
#880
b0000101100011111 #
b11011011 &
b00001101 '
1+
b000101110001000011101110 ,
#885
0+
#890
b0001001010010100 #
b01010010 &
b00111010 '
1+
b000101110001110000001101 ,
#895
0+
#900
b0111000011110010 #
b10110111 &
b10011110 '
1+
b000101110010111010100001 ,
#905
0+
#910
b0000001011010000 #
b01001000 &
b00001010 '
1+
b000101111001111110010011 ,
#915
0+
#920
b0101100010100100 #
b10110111 &
b01111100 '
1+
b000101111010001001100011 ,
#925
0+
#930
b0000010001010000 #
b10001010 &
b00001000 '
1+
b000101111111101100000111 ,
#935
0+
#940
b0010111101010110 #
b10010010 &
b01010011 '
1+
b000101111111111101010111 ,
#945
0+
#950
b0010101100010000 #
b11010100 &
b00110100 '
1+
b000110000010111010101101 ,
#955
0+
#960
b1000101111001011 #
b11101101 &
b10010111 '
1+
b000110000101100110111101 ,
#965
0+
#970
b0111000100011111 #
b11000101 &
b10010011 '
1+
b000110001110010110001000 ,
#975
0+
#980
b0001101000110100 #
b01010110 &
b01001110 '
1+
b000110010101011010100111 ,
#985
0+
#990
b0000111100000000 #
b11000000 &
b00010100 '
1+
b000110010111000011011011 ,
#995
0+
#1000
b0010001110101111 #
b10010001 &
b00111111 '
1+
b000110010111111111011011 ,
#1005
0+
#1010
b0101000011001000 #
b11011100 &
b01011110 '
1+
b000110011010001110001010 ,
#1015
0+
#1020
b0110011010101000 #
b10110100 &
b10010010 '
1+
b000110011111010001010010 ,
#1025
0+
#1030
b0100001110010111 #
b01111001 &
b10001111 '
1+
b000110100101101011111010 ,
#1035
0+
#1040
b0111111000010101 #
b10011111 &
b11001011 '
1+
b000110101001111010010001 ,
#1045
0+
#1050
b0100001111011100 #
b11001010 &
b01010110 '
1+
b000110110001110010100110 ,
#1055
0+
#1060
b0000011101100010 #
b01101001 &
b00010010 '
1+
b000110110110000010000010 ,
#1065
0+
#1070
b0000110010000001 #
b01100001 &
b00100001 '
1+
b000110110110011111100100 ,
#1075
0+
#1080
b1000001101000101 #
b10001111 &
b11101011 '
1+
b000110110111010001100101 ,
#1085
0+
#1090
b0000010101001001 #
b00101001 &
b00100001 '
1+
b000110111111011110101010 ,
#1095
0+
#1100
b0011111001000011 #
b00111111 &
b11111101 '
1+
b000110111111110011110011 ,
#1105
0+
#1110
b0000111010011100 #
b01010101 &
b00101100 '
1+
b000111000011101100110110 ,
#1115
0+
#1120
b0000111110011100 #
b10010100 &
b00011011 '
1+
b000111000100100111010010 ,
#1125
0+
#1130
b1010111101010101 #
b10111111 &
b11101011 '
1+
b000111000101100101101110 ,
#1135
0+
#1140
b0011010010000000 #
b01101001 &
b10000000 '
1+
b000111010000100011000011 ,
#1145
0+
#1150
b1111100100000110 #
b11111111 &
b11111010 '
1+
b000111010011110101000011 ,
#1155
0+
#1160
b1010010000100100 #
b10111111 &
b11011100 '
1+
b000111100011011001001001 ,
#1165
0+
#1170
b0010011110001000 #
b01011000 &
b01110011 '
1+
b000111101101101001101101 ,
#1175
0+
#1180
b0101100111001110 #
b01101110 &
b11010001 '
1+
b000111110000000111110101 ,
#1185
0+
#1190
b0000000000011100 #
b00000010 &
b00001110 '
1+
b000111110101101111000011 ,
#1195
0+
#1200
b0111110100011100 #
b10011101 &
b11001100 '
1+
b000111110101101111011111 ,
#1205
0+
#1210
b0000001001011000 #
b01100100 &
b00000110 '
1+
b000111111101100011111011 ,
#1215
0+
#1220
b1010101110011011 #
b11011111 &
b11000101 '
1+
b000111111101101101010011 ,
#1225
0+
#1230
b0001000011000010 #
b00100111 &
b01101110 '
1+
b001000001000011011101110 ,
#1235
0+
#1240
b0011011101010000 #
b10110001 &
b01010000 '
1+
b001000001001011110110000 ,
#1245
0+
#1250
b1000011000010000 #
b10001111 &
b11110000 '
1+
b001000001100111100000000 ,
#1255
0+
#1260
b0100010010010100 #
b01001101 &
b11100100 '
1+
b001000010101010100010000 ,
#1265
0+
#1270
b0001100010111000 #
b00011100 &
b11100010 '
1+
b001000011001100110100100 ,
#1275
0+
#1280
b1101101000100101 #
b11111111 &
b11011011 '
1+
b001000011011001001011100 ,
#1285
0+
#1290
b0101001101001000 #
b11001101 &
b01101000 '
1+
b001000101000110010000001 ,
#1295
0+
#1300
b0100100010000100 #
b01011011 &
b11001100 '
1+
b001000101101111111001001 ,
#1305
0+
#1310
b0000100111110100 #
b01100010 &
b00011010 '
1+
b001000110010100001001101 ,
#1315
0+
#1320
b0111101010111000 #
b10101000 &
b10111011 '
1+
b001000110011001001000001 ,
#1325
0+
#1330
b0000110010101011 #
b10001101 &
b00010111 '
1+
b001000111010110011111001 ,
#1335
0+
#1340
b0100111011000000 #
b10001100 &
b10010000 '
1+
b001000111011100110100100 ,
#1345
0+
#1350
b0000010111101101 #
b00100101 &
b00101001 '
1+
b001001000000100001100100 ,
#1355
0+
#1360
b0011000100111100 #
b01011100 &
b10001001 '
1+
b001001000000111001010001 ,
#1365
0+
#1370
b0000101100010000 #
b00110000 &
b00111011 '
1+
b001001000011111110001101 ,
#1375
0+
#1380
b0001101011011001 #
b01001111 &
b01010111 '
1+
b001001000100101010011101 ,
#1385
0+
#1390
b0000000000000000 #
b10101001 &
b00000000 '
1+
b001001000110010101110110 ,
#1395
0+
#1400
b0010010011000000 #
b10101000 &
b00111000 '
1+
#1405
0+
#1410
b1110010110110000 #
b11110000 &
b11110101 '
1+
b001001001000101000110110 ,
#1415
0+
#1420
b0000000101011100 #
b00011101 &
b00001100 '
1+
b001001010110111111100110 ,
#1425
0+
#1430
b0001011110000100 #
b11010111 &
b00011100 '
1+
b001001010111000101000010 ,
#1435
0+
#1440
b1001001111111100 #
b11100111 &
b10100100 '
1+
b001001011000100011000110 ,
#1445
0+
#1450
b0010001011001111 #
b10000101 &
b01000011 '
1+
b001001100001110011000010 ,
#1455
0+
#1460
b0110010111110111 #
b01110001 &
b11100111 '
1+
b001001100011111110010001 ,
#1465
0+
#1470
b0000100100010101 #
b01011101 &
b00011001 '
1+
b001001101010010110001000 ,
#1475
0+
#1480
b1001010010110110 #
b10100010 &
b11101011 '
1+
b001001101010111010011101 ,
#1485
0+
#1490
b0000100011010000 #
b00110000 &
b00101111 '
1+
b001001110100001101010011 ,
#1495
0+
#1500
b0010100011010111 #
b01111011 &
b01010101 '
1+
b001001110100110000100011 ,
#1505
0+
#1510
b0100100111101000 #
b01011000 &
b11010111 '
1+
b001001110111010011111010 ,
#1515
0+
#1520
b0111011001111000 #
b11011111 &
b10001000 '
1+
b001001111011111011100010 ,
#1525
0+
#1530
b0000001101101010 #
b00010011 &
b00101110 '
1+
b001010000011010101011010 ,
#1535
0+
#1540
b1010010010000000 #
b11100000 &
b10111100 '
1+
b001010000011100011000100 ,
#1545
0+
#1550
b0001100001110000 #
b00101110 &
b10001000 '
1+
b001010001101110101000100 ,
#1555
0+
#1560
b0001110010110110 #
b11110101 &
b00011110 '
1+
b001010001111010110110100 ,
#1565
0+
#1570
b0000100011001010 #
b01111101 &
b00010010 '
1+
b001010010001001001101010 ,
#1575
0+
#1580
b0000110111110010 #
b00101010 &
b01010101 '
1+
b001010010001101100110100 ,
#1585
0+
#1590
b0000001100001110 #
b00101110 &
b00010001 '
1+
b001010010010100100100110 ,
#1595
0+
#1600
b1010111000011011 #
b11111001 &
b10110011 '
1+
b001010010010110000110100 ,
#1605
0+
#1610
b0010001011001000 #
b01010100 &
b01101010 '
1+
b001010011101101001001111 ,
#1615
0+
#1620
b0110101111000110 #
b10011011 &
b10110010 '
1+
b001010011111110100010111 ,
#1625
0+
#1630
b0001111101110100 #
b10000100 &
b00111101 '
1+
b001010100110100011011101 ,
#1635
0+
#1640
b0110111001100100 #
b10011101 &
b10110100 '
1+
b001010101000100001010001 ,
#1645
0+
#1650
b0000101000100000 #
b01101100 &
b00011000 '
1+
b001010101111011010110101 ,
#1655
0+
#1660
b0000011110110010 #
b00001010 &
b11000101 '
1+
b001010110000000011010101 ,
#1665
0+
#1670
b1101100110000111 #
b11101111 &
b11101001 '
1+
b001010110000100010000111 ,
#1675
0+
#1680
b0000000010011010 #
b01001101 &
b00000010 '
1+
b001010111110001000001110 ,
#1685
0+
#1690
b0000010000001011 #
b00010111 &
b00101101 '
1+
b001010111110001010101000 ,
#1695
0+
#1700
b0011001101111011 #
b10111111 &
b01000101 '
1+
b001010111110011010110011 ,
#1705
0+
#1710
b0111111101000100 #
b10110101 &
b10110100 '
1+
b001011000001101000101110 ,
#1715
0+
#1720
b0001001110111001 #
b01100011 &
b00110011 '
1+
b001011001001100101110010 ,
#1725
0+
#1730
b0110110100001110 #
b11000110 &
b10001101 '
1+
b001011001010110100101011 ,
#1735
0+
#1740
b1000000110100000 #
b10001000 &
b11110100 '
1+
b001011010001101000111001 ,
#1745
0+
#1750
b0100111110011110 #
b10011110 &
b10000001 '
1+
b001011011001101111011001 ,
#1755
0+
#1760
b1001111101111000 #
b10101000 &
b11110011 '
1+
b001011011110101101110111 ,
#1765
0+
#1770
b0011110111000100 #
b11101100 &
b01000011 '
1+
b001011101000101011101111 ,
#1775
0+
#1780
b0100100000110000 #
b10100101 &
b01110000 '
1+
b001011101100100010110011 ,
#1785
0+
#1790
b0010000100000000 #
b10000000 &
b01000010 '
1+
b001011110001000011100011 ,
#1795
0+
#1800
b0010000101010100 #
b00100100 &
b11101101 '
1+
b001011110011000111100011 ,
#1805
0+
#1810
b0001000000101100 #
b01011010 &
b00101110 '
1+
b001011110101001100110111 ,
#1815
0+
#1820
b0011001011000010 #
b10110010 &
b01001001 '
1+
b001011110110001101100011 ,
#1825
0+
#1830
b0001011011101001 #
b00010111 &
b11111111 '
1+
b001011111001011000100101 ,
#1835
0+
#1840
b0000110110101000 #
b01001100 &
b00101110 '
1+
b001011111010110100001110 ,
#1845
0+
#1850
b0000000111101111 #
b00101101 &
b00001011 '
1+
b001011111011101010110110 ,
#1855
0+
#1860
b0110010110000110 #
b01110011 &
b11100010 '
1+
b001011111011110010100101 ,
#1865
0+
#1870
b1001111110101010 #
b10111111 &
b11010110 '
1+
b001100000010001000101011 ,
#1875
0+
#1880
b0000101011101001 #
b00010101 &
b10000101 '
1+
b001100001100000111010101 ,
#1885
0+
#1890
b0011110010110111 #
b01100011 &
b10011101 '
1+
b001100001100110010111110 ,
#1895
0+
#1900
b0000000011110010 #
b01111001 &
b00000010 '
1+
b001100010000100101110101 ,
#1905
0+
#1910
b0000001111111111 #
b00011111 &
b00100001 '
1+
b001100010000101001100111 ,
#1915
0+
#1920
b0000101010000111 #
b11110101 &
b00001011 '
1+
b001100010000111001100110 ,
#1925
0+
#1930
b0011110000101000 #
b01100100 &
b10011010 '
1+
b001100010001100011101101 ,
#1935
0+
#1940
b0110111000000111 #
b01111011 &
b11100101 '
1+
b001100010101010100010101 ,
#1945
0+
#1950
b1000100010100100 #
b11011100 &
b10011111 '
1+
b001100011100001100011100 ,
#1955
0+
#1960
b0010110001001100 #
b11010010 &
b00110110 '
1+
b001100100100101111000000 ,
#1965
0+
#1970
b0110101000111000 #
b11001110 &
b10000100 '
1+
b001100100111100000001100 ,
#1975
0+
#1980
b0111000110011011 #
b01111111 &
b11100101 '
1+
b001100101110001001000100 ,
#1985
0+
#1990
b0110011111100001 #
b10000011 &
b11001011 '
1+
b001100110101001111011111 ,
#1995
0+
#2000
b0000110111000000 #
b00010100 &
b10110000 '
1+
b001100111011101111000000 ,
#2005
0+
#2010
b0111000011011010 #
b11010110 &
b10000111 '
1+
b001100111100100110000000 ,
#2015
0+
#2020
b0101010110001111 #
b10010011 &
b10010101 '
1+
b001101000011101001011010 ,
#2025
0+
#2030
b0011110110110000 #
b01011110 &
b10101000 '
1+
b001101001000111111101001 ,
#2035
0+
#2040
b0001001110011010 #
b00011010 &
b11000001 '
1+
b001101001100110110011001 ,
#2045
0+
#2050
b0010100001111000 #
b01000110 &
b10010100 '
1+
b001101001110000100110011 ,
#2055
0+
#2060
b0100110011101111 #
b11000011 &
b01100101 '
1+
b001101010000100110101011 ,
#2065
0+
#2070
b1000001000011000 #
b10110101 &
b10111000 '
1+
b001101010101011010011010 ,
#2075
0+
#2080
b0000101101100000 #
b01110000 &
b00011010 '
1+
b001101011101100010110010 ,
#2085
0+
#2090
b0100101101000110 #
b01010010 &
b11101011 '
1+
b001101011110010000010010 ,
#2095
0+
#2100
b0010110111010010 #
b11111111 &
b00101110 '
1+
b001101100010111101011000 ,
#2105
0+
#2110
b0111000010101010 #
b10001010 &
b11010001 '
1+
b001101100101110100101010 ,
#2115
0+
#2120
b0010001001100000 #
b01100100 &
b01011000 '
1+
b001101101100110111010100 ,
#2125
0+
#2130
b0100101110110100 #
b01010101 &
b11100100 '
1+
b001101101111000000110100 ,
#2135
0+
#2140
b0011010001010000 #
b00111110 &
b11011000 '
1+
b001101110011101111101000 ,
#2145
0+
#2150
b0011100000001110 #
b10101111 &
b01010010 '
1+
b001101110111000000111000 ,
#2155
0+
#2160
b0100011110110110 #
b10001001 &
b10000110 '
1+
b001101111010100001000110 ,
#2165
0+
#2170
b0001011110111100 #
b11011001 &
b00011100 '
1+
b001101111110111111111100 ,
#2175
0+
#2180
b0000010111001101 #
b00011011 &
b00110111 '
1+
b001110000000011110111000 ,
#2185
0+
#2190
b0010100101011000 #
b11000100 &
b00110110 '
1+
b001110000000110110000101 ,
#2195
0+
#2200
b0000100110111010 #
b11111001 &
b00001010 '
1+
b001110000011011011011101 ,
#2205
0+
#2210
b1001010001011000 #
b11001010 &
b10111100 '
1+
b001110000100000010010111 ,
#2215
0+
#2220
b0011011100010001 #
b01101111 &
b01111111 '
1+
b001110001101010011101111 ,
#2225
0+
#2230
b0110010111101011 #
b01110101 &
b11011111 '
1+
b001110010000110000000000 ,
#2235
0+
#2240
b0111011011101111 #
b10011001 &
b11000111 '
1+
b001110010111000111101011 ,
#2245
0+
#2250
b0111011111110000 #
b11001010 &
b10011000 '
1+
b001110011110100011011010 ,
#2255
0+
#2260
b0101000110101110 #
b11110110 &
b01010101 '
1+
b001110100110000011001010 ,
#2265
0+
#2270
b0010010011101010 #
b01101001 &
b01011010 '
1+
b001110101011001001111000 ,
#2275
0+
#2280
b1000000001100110 #
b10101101 &
b10111110 '
1+
b001110101101011101100010 ,
#2285
0+
#2290
b0011100011101010 #
b00111110 &
b11101011 '
1+
b001110110101011111001000 ,
#2295
0+
#2300
b1000110001100010 #
b10010111 &
b11101110 '
1+
b001110111001000010110010 ,
#2305
0+
#2310
b0000011110100000 #
b00111101 &
b00100000 '
1+
b001111000001110100010100 ,
#2315
0+
#2320
b0000101001101100 #
b01110100 &
b00010111 '
1+
b001111000010010010110100 ,
#2325
0+
#2330
b0010000110000100 #
b00111100 &
b10001111 '
1+
b001111000010111100100000 ,
#2335
0+
#2340
b0000000000000000 #
b01001110 &
b00000000 '
1+
b001111000101000010100100 ,
#2345
0+
#2350
b0011011010100011 #
b11000101 &
b01000111 '
1+
#2355
0+
#2360
b0000011000100101 #
b00001011 &
b10001111 '
1+
b001111001000011101000111 ,
#2365
0+
#2370
b0000000111101000 #
b00000100 &
b01111010 '
1+
b001111001000110101101100 ,
#2375
0+
#2380
b0000011100010111 #
b00001111 &
b01111001 '
1+
b001111001000111101010100 ,
#2385
0+
#2390
b0011101100010000 #
b01011010 &
b10101000 '
1+
b001111001001011001101011 ,
#2395
0+
#2400
b0000100100000000 #
b01000000 &
b00100100 '
1+
b001111001101000101111011 ,
#2405
0+
#2410
b0000110110110110 #
b01000001 &
b00110110 '
1+
b001111001101101001111011 ,
#2415
0+
#2420
b0101000001011010 #
b01111001 &
b10101010 '
1+
b001111001110100000110001 ,
#2425
0+
#2430
b0001011000010111 #
b10010001 &
b00100111 '
1+
b001111010011100010001011 ,
#2435
0+
#2440
b0101010011100111 #
b01101001 &
b11001111 '
1+
b001111010100111010100010 ,
#2445
0+
#2450
b0000000000000000 #
b00010010 &
b00000000 '
1+
b001111011010001110001001 ,
#2455
0+
#2460
b0011101100010000 #
b10111101 &
b01010000 '
1+
#2465
0+
#2470
b0000011000100000 #
b00100000 &
b00110001 '
1+
b001111011101111010011001 ,
#2475
0+
#2480
b0010010100000100 #
b01100111 &
b01011100 '
1+
b001111011110010010111001 ,
#2485
0+
#2490
b1000100001110101 #
b11000001 &
b10110101 '
1+
b001111100000100110111101 ,
#2495
0+
#2500
b0011000000101000 #
b01011100 &
b10000110 '
1+
b001111101001001000110010 ,
#2505
0+
#2510
b0110010111001011 #
b11111101 &
b01100111 '
1+
b001111101100001001011010 ,
#2515
0+
#2520
b0000000000010110 #
b00010110 &
b00000001 '
1+
b001111110010100000100101 ,
#2525
0+
#2530
b0010000010101010 #
b11100010 &
b00100101 '
1+
b001111110010100000111011 ,
#2535
0+
#2540
b0001110010011000 #
b01111010 &
b00111100 '
1+
b001111110100100011100101 ,
#2545
0+
#2550
b1001010011110010 #
b11001101 &
b10111010 '
1+
b001111110110010101111101 ,
#2555
0+
#2560
b0000010101000000 #
b01100000 &
b00001110 '
1+
b001111111111101001101111 ,
#2565
0+
#2570
b1100110100111010 #
b11110001 &
b11011010 '
1+
b001111111111111110101111 ,
#2575
0+
#2580
b0101110111110010 #
b10111001 &
b10000010 '
1+
b010000001100110011101001 ,
#2585
0+
#2590
b0000000000100010 #
b00000001 &
b00100010 '
1+
b010000010010101011011011 ,
#2595
0+
#2600
b0000011000000011 #
b01010001 &
b00010011 '
1+
b010000010010101011111101 ,
#2605
0+
#2610
b0000000111111110 #
b00100010 &
b00001111 '
1+
b010000010011000100000000 ,
#2615
0+
#2620
b0001100110000110 #
b01100011 &
b01000010 '
1+
b010000010011001011111110 ,
#2625
0+
#2630
b0011001010000000 #
b01000000 &
b11001010 '
1+
b010000010100110010000100 ,
#2635
0+
#2640
b0000000010011110 #
b10011110 &
b00000001 '
1+
b010000010111111100000100 ,
#2645
0+
#2650
b0111110100000000 #
b10000000 &
b11111010 '
1+
b010000010111111110100010 ,
#2655
0+
#2660
b0100001001101000 #
b10001000 &
b01111101 '
1+
b010000011111110010100010 ,
#2665
0+
#2670
b0011110001111100 #
b01100010 &
b10011110 '
1+
b010000100011111100001010 ,
#2675
0+
#2680
b0010000101111000 #
b01111110 &
b01000100 '
1+
b010000100111101110000110 ,
#2685
0+
#2690
b1011110011101000 #
b11000011 &
b11111000 '
1+
b010000101001110011111110 ,
#2695
0+
#2700
b0100100000000000 #
b10000000 &
b10010000 '
1+
b010000110101100111100110 ,
#2705
0+
#2710
b1001101111000000 #
b10110010 &
b11100000 '
1+
b010000111010000111100110 ,
#2715
0+
#2720
b0110010100111101 #
b10011111 &
b10100011 '
1+
b010001000011110110100110 ,
#2725
0+
#2730
b0011111111110000 #
b10111010 &
b01011000 '
1+
b010001001010001011100011 ,
#2735
0+
#2740
b0001101100000111 #
b00100101 &
b10111011 '
1+
b010001001110001011010011 ,
#2745
0+
#2750
b0011100010110110 #
b01111010 &
b01110111 '
1+
b010001001111110111011010 ,
#2755
0+
#2760
b0111111000100100 #
b11001111 &
b10011100 '
1+
b010001010011011010010000 ,
#2765
0+
#2770
b0001101000101100 #
b10000110 &
b00110010 '
1+
b010001011011010010110100 ,
#2775
0+
#2780
b1010101110110100 #
b11011110 &
b11000110 '
1+
b010001011100111011100000 ,
#2785
0+
