src/macPipe.sv
module macPipe #(
	parameter int WIDTH = 8
)(
	input logic [WIDTH-1:0] A, B, 
	input logic rst, acc, valid_in, clk,
	output logic [WIDTH*3-1:0] result, 
	output logic valid_out
);
	reg [WIDTH*2-1:0] mul_reg;
	reg acc_reg;
	reg valid;

	always_ff @(posedge clk) begin
		acc_reg <= acc;
		valid <= valid_in;

		case ({rst, valid_in})
			2'b10: begin
				mul_reg <= 0;
				valid <= 0;
				acc_reg <= 0;
			end
			2'b11: begin
				mul_reg <= 0;
				valid <= 0;
				acc_reg <= 0;
			end
			2'b00: mul_reg <= mul_reg;
			2'b01: mul_reg <= (WIDTH*2)'(A) * (WIDTH*2)'(B);
		endcase
	end

	always_ff @(posedge clk) begin
		valid_out <= valid;

		case ({rst, valid, acc_reg})
			3'b101: begin
				result <= 0;
				valid_out <= 0;
			end
			3'b111: begin
				result <= 0;
				valid_out <= 0;
			end
			3'b100: begin
				result <= 0;
				valid_out <= 0;
			end
			3'b110: begin
				result <= 0;
				valid_out <= 0;
			end
			3'b000: result <= result;
			3'b001: result <= result;
			3'b010: result <= {{(WIDTH){1'b0}}, mul_reg};
			3'b011: result <= result + {{(WIDTH){1'b0}}, mul_reg};
		endcase		
	end
endmodule

src/dump.vcd
$version Generated by VerilatedVcd $end
$timescale 1ps $end
 $scope module TOP $end
  $var wire 8 & A [7:0] $end
  $var wire 8 ' B [7:0] $end
  $var wire 1 ( rst $end
  $var wire 1 ) acc $end
  $var wire 1 * valid_in $end
  $var wire 1 + clk $end
  $var wire 24 , result [23:0] $end
  $var wire 1 - valid_out $end
  $scope module macPipe $end
   $var wire 32 . WIDTH [31:0] $end
   $var wire 8 & A [7:0] $end
   $var wire 8 ' B [7:0] $end
   $var wire 1 ( rst $end
   $var wire 1 ) acc $end
   $var wire 1 * valid_in $end
   $var wire 1 + clk $end
   $var wire 24 , result [23:0] $end
   $var wire 1 - valid_out $end
   $var wire 16 # mul_reg [15:0] $end
   $var wire 1 $ acc_reg $end
   $var wire 1 % valid $end
  $upscope $end
 $upscope $end
$enddefinitions $end


#0
b0000000000000000 #
0$
0%
b00000000 &
b00000000 '
1(
1)
0*
0+
b000000000000000000000000 ,
0-
b00000000000000000000000000001000 .
#10
1+
#20
0(
1*
0+
#30
b0101010001101110 #
1$
1%
b11010110 &
b01100101 '
1+
#35
0+
#40
b0111011111100000 #
b11100000 &
b10001001 '
1+
b000000000101010001101110 ,
1-
#45
0+
#50
b0001100011010110 #
b00100010 &
b10111011 '
1+
b000000001100110001001110 ,
#55
0+
#60
b0111001110011000 #
b10001001 &
b11011000 '
1+
b000000001110010100100100 ,
#65
0+
#70
b0010100010101110 #
b11111110 &
b00101001 '
1+
b000000010101100010111100 ,
#75
0+
#80
b0010110010010000 #
b11111000 &
b00101110 '
1+
b000000011000000101101010 ,
#85
0+
#90
b0001010111010110 #
b10000010 &
b00101011 '
1+
b000000011010110111111010 ,
#95
0+
#100
b1010001000101100 #
b11000010 &
b11010110 '
1+
b000000011100001111010000 ,
#105
0+
#110
b1101111100100000 #
b11100000 &
b11111111 '
1+
b000000100110010111111100 ,
#115
0+
#120
b0000011101000100 #
b00010100 &
b01011101 '
1+
b000000110100010100011100 ,
#125
0+
#130
b0001010011000001 #
b11111101 &
b00010101 '
1+
b000000110100110001100000 ,
#135
0+
#140
b0000000111100000 #
b10100000 &
b00000011 '
1+
b000000110110000100100001 ,
#145
0+
#150
b0000001111110100 #
b00101110 &
b00010110 '
1+
b000000110110001100000001 ,
#155
0+
#160
b0111010000110111 #
b11010011 &
b10001101 '
1+
b000000110110011011110101 ,
#165
0+
#170
b0010101010110110 #
b01000111 &
b10011010 '
1+
b000000111101101100101100 ,
#175
0+
#180
b0000110000000010 #
b01101010 &
b00011101 '
1+
b000001000000010111100010 ,
#185
0+
#190
b0000000000000000 #
b00000000 &
b01001011 '
1+
b000001000001000111100100 ,
#195
0+
#200
b0001011000001100 #
b10100110 &
b00100010 '
1+
#205
0+
#210
b0000000100011010 #
b00000110 &
b00101111 '
1+
b000001000010011111110000 ,
#215
0+
#220
b0000001111101100 #
b11111011 &
b00000100 '
1+
b000001000010100100001010 ,
#225
0+
#230
b0101001110001000 #
b01011000 &
b11110011 '
1+
b000001000010110011110110 ,
#235
0+
#240
b0010101011000110 #
b00110010 &
b11011011 '
1+
b000001001000000001111110 ,
#245
0+
#250
b0001110010011000 #
b00011110 &
b11110100 '
1+
b000001001010101101000100 ,
#255
0+
#260
b1010111110011110 #
b10110001 &
b11111110 '
1+
b000001001100011111011100 ,
#265
0+
#270
b1011101111110010 #
b11110011 &
b11000110 '
1+
b000001010111011101111010 ,
#275
0+
#280
b0101010101010000 #
b01011011 &
b11110000 '
1+
b000001100011001101101100 ,
#285
0+
#290
b1101011010111001 #
b11011011 &
b11111011 '
1+
b000001101000100010111100 ,
#295
0+
#300
b0000100010010100 #
b11110100 &
b00001001 '
1+
b000001110101111101110101 ,
#305
0+
#310
b0000110100110111 #
b00010001 &
b11000111 '
1+
b000001110110100000001001 ,
#315
0+
#320
b0011001110010000 #
b10010110 &
b01011000 '
1+
b000001110111010101000000 ,
#325
0+
#330
b0000000001100010 #
b01100010 &
b00000001 '
1+
b000001111010100011010000 ,
#335
0+
#340
b0010110011001010 #
b01110101 &
b01100010 '
1+
b000001111010100100110010 ,
#345
0+
#350
b0000100000000100 #
b01001100 &
b00011011 '
1+
b000001111101010111111100 ,
#355
0+
#360
b0010101001001000 #
b10000100 &
b01010010 '
1+
b000001111101111000000000 ,
#365
0+
#370
b0010010100110101 #
b01001011 &
b01111111 '
1+
b000010000000100001001000 ,
#375
0+
#380
b0011011011000010 #
b01010110 &
b10100011 '
1+
b000010000010110101111101 ,
#385
0+
#390
b0011110010010000 #
b01110010 &
b10001000 '
1+
b000010000110010000111111 ,
#395
0+
#400
b0100011011100000 #
b01111110 &
b10010000 '
1+
b000010001010000011001111 ,
#405
0+
#410
b0001011101110000 #
b01111101 &
b00110000 '
1+
b000010001110011110101111 ,
#415
0+
#420
b0011111010010000 #
b10001111 &
b01110000 '
1+
b000010001111111100011111 ,
#425
0+
#430
b1110000011011100 #
b11110110 &
b11101010 '
1+
b000010010011110110101111 ,
#435
0+
#440
b0100111100110001 #
b01100001 &
b11010001 '
1+
b000010100001111010001011 ,
#445
0+
#450
b0100110001011110 #
b11100110 &
b01010101 '
1+
b000010100110110110111100 ,
#455
0+
#460
b1101001001010110 #
b11011010 &
b11110111 '
1+
b000010101011101000011010 ,
#465
0+
#470
b0000110001000000 #
b00011100 &
b01110000 '
1+
b000010111000110001110000 ,
#475
0+
#480
b0010011101100000 #
b01010000 &
b01111110 '
1+
b000010111001100010110000 ,
#485
0+
#490
b0101011011110101 #
b01110001 &
b11000101 '
1+
b000010111100000000010000 ,
#495
0+
#500
b1010010101100000 #
b11100000 &
b10111101 '
1+
b000011000001011100000101 ,
#505
0+
#510
b0101100011000101 #
b11100001 &
b01100101 '
1+
b000011001011110001100101 ,
#515
0+
#520
b0000001010010100 #
b00001111 &
b00101100 '
1+
b000011010001010100101010 ,
#525
0+
#530
b0101100111110100 #
b11100100 &
b01100101 '
1+
b000011010001011110111110 ,
#535
0+
#540
b0100011001011001 #
b11001111 &
b01010111 '
1+
b000011010111000110110010 ,
#545
0+
#550
b0100100010000100 #
b11101110 &
b01001110 '
1+
b000011011011100000001011 ,
#555
0+
#560
b0110000010001101 #
b11100111 &
b01101011 '
1+
b000011100000000010001111 ,
#565
0+
#570
b0011101000010100 #
b01111110 &
b01110110 '
1+
b000011100110000100011100 ,
#575
0+
#580
b0110001100111100 #
b11011011 &
b01110100 '
1+
b000011101001101100110000 ,
#585
0+
#590
b0001011010111100 #
b01100001 &
b00111100 '
1+
b000011101111111001101100 ,
#595
0+
#600
b0001001100100011 #
b01000101 &
b01000111 '
1+
b000011110001010100101000 ,
#605
0+
#610
b0001000110001111 #
b10010001 &
b00011111 '
1+
b000011110010100001001011 ,
#615
0+
#620
b0010101000100100 #
b00111110 &
b10101110 '
1+
b000011110011100111011010 ,
#625
0+
#630
b0100111101010010 #
b10001111 &
b10001110 '
1+
b000011110110001111111110 ,
#635
0+
#640
b0000000000101100 #
b00101100 &
b00000001 '
1+
b000011111011001101010000 ,
#645
0+
#650
b0000010001000100 #
b01010100 &
b00001101 '
1+
b000011111011001101111100 ,
#655
0+
#660
b0010011101010110 #
b10111110 &
b00110101 '
1+
b000011111011011111000000 ,
#665
0+
#670
b0101101110111100 #
b01110010 &
b11001110 '
1+
b000011111101111100010110 ,
#675
0+
#680
b0010000010010110 #
b01100001 &
b01010110 '
1+
b000100000011101011010010 ,
#685
0+
#690
b0000100110010000 #
b00110011 &
b00110000 '
1+
b000100000101101101101000 ,
#695
0+
#700
b0001011001001101 #
b10101101 &
b00100001 '
1+
b000100000110010011111000 ,
#705
0+
#710
b0100100101010110 #
b01111110 &
b10010101 '
1+
b000100000111101101000101 ,
#715
0+
#720
b1000100111010000 #
b10001100 &
b11111100 '
1+
b000100001100010010011011 ,
#725
0+
#730
b0000010001111000 #
b00001011 &
b01101000 '
1+
b000100010100111001101011 ,
#735
0+
#740
b0010111101000000 #
b01110000 &
b01101100 '
1+
b000100010101001011100011 ,
#745
0+
#750
b0111001111110100 #
b10100100 &
b10110101 '
1+
b000100011000001000100011 ,
#755
0+
#760
b0010010111000010 #
b10110011 &
b00110110 '
1+
b000100011111011000010111 ,
#765
0+
#770
b1100100001101000 #
b11010100 &
b11110010 '
1+
b000100100001101111011001 ,
#775
0+
#780
b0101100100010000 #
b11100100 &
b01100100 '
1+
b000100101110010001000001 ,
#785
0+
#790
b0000100000000000 #
b10000000 &
b00010000 '
1+
b000100110011110101010001 ,
#795
0+
#800
b0101001110100100 #
b01100101 &
b11010100 '
1+
b000100110100010101010001 ,
#805
0+
#810
b0000001111110111 #
b00011101 &
b00100011 '
1+
b000100111001100011110101 ,
#815
0+
#820
b0000010100000111 #
b00001001 &
b10001111 '
1+
b000100111001110011101100 ,
#825
0+
#830
b0110001111001010 #
b11110001 &
b01101010 '
1+
b000100111010000111110011 ,
#835
0+
#840
b0010000100111110 #
b11100110 &
b00100101 '
1+
b000101000000010110111101 ,
#845
0+
#850
b0101100100000001 #
b10011011 &
b10010011 '
1+
b000101000010011011111011 ,
#855
0+
#860
b0000011011010110 #
b01000110 &
b00011001 '
1+
b000101000111111111111100 ,
#865
0+
#870
b0010000011111000 #
b00101000 &
b11010011 '
1+
b000101001000011011010010 ,
#875
0+
#880
b0000010001111000 #
b00010110 &
b00110100 '
1+
b000101001010011111001010 ,
#885
0+
#890
b0001111011100010 #
b00111011 &
b10000110 '
1+
b000101001010110001000010 ,
#895
0+
#900
b1000101101100000 #
b10100000 &
b11011111 '
1+
b000101001100101100100100 ,
#905
0+
#910
b0001001110110000 #
b00111100 &
b01010100 '
1+
b000101010101011010000100 ,
#915
0+
#920
b0000000101010000 #
b00010101 &
b00010000 '
1+
b000101010110101000110100 ,
#925
0+
#930
b0100010000010110 #
b01000110 &
b11111001 '
1+
b000101010110101110000100 ,
#935
0+
#940
b0101100110111000 #
b01110100 &
b11000110 '
1+
b000101011010111110011010 ,
#945
0+
#950
b0000100001111010 #
b00001010 &
b11011001 '
1+
b000101100000100101010010 ,
#955
0+
#960
b0001011110011101 #
b10011011 &
b00100111 '
1+
b000101100001000111001100 ,
#965
0+
#970
b1010001000010100 #
b11111101 &
b10100100 '
1+
b000101100010100101101001 ,
#975
0+
#980
b1010101000100010 #
b10110111 &
b11101110 '
1+
b000101101100101101111101 ,
#985
0+
#990
b0000100100110011 #
b00001111 &
b10011101 '
1+
b000101110111010110011111 ,
#995
0+
#1000
b0000110010011110 #
b00010011 &
b10101010 '
1+
b000101110111111011010010 ,
#1005
0+
#1010
b0001000011100000 #
b00110000 &
b01011010 '
1+
b000101111000101101110000 ,
#1015
0+
#1020
b0100001111001011 #
b11000011 &
b01011001 '
1+
b000101111001110001010000 ,
#1025
0+
#1030
b0010011000100101 #
b00101101 &
b11011001 '
1+
b000101111110000000011011 ,
#1035
0+
#1040
b0011100101001000 #
b10001101 &
b01101000 '
1+
b000110000000011001000000 ,
#1045
0+
#1050
b0001000011100000 #
b01100000 &
b00101101 '
1+
b000110000011111110001000 ,
#1055
0+
#1060
b0010101101000100 #
b01000111 &
b10011100 '
1+
b000110000101000001101000 ,
#1065
0+
#1070
b0010111011011101 #
b10000001 &
b01011101 '
1+
b000110000111101110101100 ,
#1075
0+
#1080
b1000010110110100 #
b10101100 &
b11000111 '
1+
b000110001010101010001001 ,
#1085
0+
#1090
b0000101100010110 #
b01010110 &
b00100001 '
1+
b000110010011000000111101 ,
#1095
0+
#1100
b0011010101000000 #
b10001110 &
b01100000 '
1+
b000110010011101101010011 ,
#1105
0+
#1110
b0010100000001010 #
b11111010 &
b00101001 '
1+
b000110010111000010010011 ,
#1115
0+
#1120
b1000001100111000 #
b10001000 &
b11110111 '
1+
b000110011001100010011101 ,
#1125
0+
#1130
b0011001001110011 #
b11001101 &
b00111111 '
1+
b000110100001101111010101 ,
#1135
0+
#1140
b1100010110101000 #
b11100110 &
b11011100 '
1+
b000110100100111001001000 ,
#1145
0+
#1150
b1101010111111100 #
b11011100 &
b11111001 '
1+
b000110110001001111110000 ,
#1155
0+
#1160
b0000011001001000 #
b10000110 &
b00001100 '
1+
b000110111110100111101100 ,
#1165
0+
#1170
b0001011111111110 #
b01010011 &
b01001010 '
1+
b000110111111000000110100 ,
#1175
0+
#1180
b0011001010000000 #
b01100101 &
b10000000 '
1+
b000111000000100000110010 ,
#1185
0+
#1190
b0010000100010110 #
b00100011 &
b11110010 '
1+
b000111000011101010110010 ,
#1195
0+
#1200
b0111011010111000 #
b11101000 &
b10000011 '
1+
b000111000101101111001000 ,
#1205
0+
#1210
b0000011000000000 #
b00100000 &
b00110000 '
1+
b000111001101001010000000 ,
#1215
0+
#1220
b0001001101111111 #
b00011111 &
b10100001 '
1+
b000111001101100010000000 ,
#1225
0+
#1230
b0111000001011100 #
b10001101 &
b11001100 '
1+
b000111001110101111111111 ,
#1235
0+
#1240
b0101110100011011 #
b01101001 &
b11100011 '
1+
b000111010101110001011011 ,
#1245
0+
#1250
b1110010010101011 #
b11101101 &
b11110111 '
1+
b000111011011100101110110 ,
#1255
0+
#1260
b0011110101011100 #
b01000100 &
b11100111 '
1+
b000111101001111000100001 ,
#1265
0+
#1270
b0001100110000000 #
b00100000 &
b11001100 '
1+
b000111101101101101111101 ,
#1275
0+
#1280
b1100111001110011 #
b11011111 &
b11101101 '
1+
b000111101111010011111101 ,
#1285
0+
#1290
b0000100001110111 #
b00001011 &
b11000101 '
1+
b000111111100001101110000 ,
#1295
0+
#1300
b1011011001000110 #
b11001010 &
b11100111 '
1+
b000111111100101111100111 ,
#1305
0+
#1310
b0011101101100000 #
b10111110 &
b01010000 '
1+
b001000001000001000101101 ,
#1315
0+
#1320
b0001000100010110 #
b11110011 &
b00010010 '
1+
b001000001011110110001101 ,
#1325
0+
#1330
b0011010110001010 #
b10011010 &
b01011001 '
1+
b001000001100111010100011 ,
#1335
0+
#1340
b0110110001011100 #
b10010010 &
b10111110 '
1+
b001000010000010000101101 ,
#1345
0+
#1350
b0010010000001001 #
b01001011 &
b01111011 '
1+
b001000010111000010001001 ,
#1355
0+
#1360
b0001101100101011 #
b01000001 &
b01101011 '
1+
b001000011001010010010010 ,
#1365
0+
#1370
b0100000011001011 #
b10101011 &
b01100001 '
1+
b001000011010111110111101 ,
#1375
0+
#1380
b0000001011011000 #
b00001101 &
b00111000 '
1+
b001000011111000010001000 ,
#1385
0+
#1390
b0001010010111110 #
b00101101 &
b01110110 '
1+
b001000011111001101100000 ,
#1395
0+
#1400
b0000001010111110 #
b00011011 &
b00011010 '
1+
b001000100000100000011110 ,
#1405
0+
#1410
b0010100001110011 #
b01101101 &
b01011111 '
1+
b001000100000101011011100 ,
#1415
0+
#1420
b0000000010001101 #
b00000001 &
b10001101 '
1+
b001000100011001101001111 ,
#1425
0+
#1430
b0010010110100000 #
b00101011 &
b11100000 '
1+
b001000100011001111011100 ,
#1435
0+
#1440
b0001100110111100 #
b01111010 &
b00110110 '
1+
b001000100101100101111100 ,
#1445
0+
#1450
b0010101111010100 #
b10100101 &
b01000100 '
1+
b001000100111001100111000 ,
#1455
0+
#1460
b0000101101010100 #
b00011101 &
b01100100 '
1+
b001000101001111100001100 ,
#1465
0+
#1470
b0000100111100101 #
b10010101 &
b00010001 '
1+
b001000101010101001100000 ,
#1475
0+
#1480
b0001010110101010 #
b01110110 &
b00101111 '
1+
b001000101011010001000101 ,
#1485
0+
#1490
b0000001101010000 #
b01101010 &
b00001000 '
1+
b001000101100100111101111 ,
#1495
0+
#1500
b1010011110010001 #
b11101101 &
b10110101 '
1+
b001000101100110100111111 ,
#1505
0+
#1510
b0001100000001101 #
b10000011 &
b00101111 '
1+
b001000110111010011010000 ,
#1515
0+
#1520
b0000010111101110 #
b00100001 &
b00101110 '
1+
b001000111000110011011101 ,
#1525
0+
#1530
b0001100111100000 #
b10010000 &
1+
b001000111001001011001011 ,
#1535
0+
#1540
b0100101101001110 #
b01100110 &
b10111101 '
1+
b001000111010110010101011 ,
#1545
0+
#1550
b0101001101001000 #
b10100100 &
b10000010 '
1+
b001000111111011111111001 ,
#1555
0+
#1560
b0000111001000111 #
b11010111 &
b00010001 '
1+
b001001000100101101000001 ,
#1565
0+
#1570
b1011110111011000 #
b11100001 &
b11011000 '
1+
b001001000101100110001000 ,
#1575
0+
#1580
b0000100000000110 #
b10011110 &
b00001101 '
1+
b001001010001011101100000 ,
#1585
0+
#1590
b0001000101011000 #
b10111001 &
b00011000 '
1+
b001001010001111101100110 ,
#1595
0+
#1600
b0001100010011010 #
b01000011 &
b01011110 '
1+
b001001010011000010111110 ,
#1605
0+
#1610
b0010001100111101 #
b01011101 &
b01100001 '
1+
b001001010100100101011000 ,
#1615
0+
#1620
b1011011101100100 #
b11000010 &
b11110010 '
1+
b001001010110110010010101 ,
#1625
0+
#1630
b0001100011110000 #
b01110010 &
b00111000 '
1+
b001001100010001111111001 ,
#1635
0+
#1640
b0001110001011100 #
b00100001 &
b11011100 '
1+
b001001100011110011101001 ,
#1645
0+
#1650
b0000001111001111 #
b01000001 &
b00001111 '
1+
b001001100101100101000101 ,
#1655
0+
#1660
b0110111100000100 #
b10010001 &
b11000100 '
1+
b001001100101110100010100 ,
#1665
0+
#1670
b0010101100011100 #
b00111110 &
b10110010 '
1+
b001001101100110000011000 ,
#1675
0+
#1680
b1100001110001010 #
b11110011 &
b11001110 '
1+
b001001101111011100110100 ,
#1685
0+
#1690
b0100110111100000 #
b11100000 &
b01011001 '
1+
b001001111011101010111110 ,
#1695
0+
#1700
b0100011110101100 #
b10001011 &
b10000100 '
1+
b001010000000100010011110 ,
#1705
0+
#1710
b0101001111010110 #
b11011011 &
b01100010 '
1+
b001010000101000001001010 ,
#1715
0+
#1720
b0110111000000001 #
b10010101 &
b10111101 '
1+
b001010001010010000100000 ,
#1725
0+
#1730
b0000101110001110 #
b00111010 &
b00110011 '
1+
b001010010001001000100001 ,
#1735
0+
#1740
b1011111110111110 #
b11001010 &
b11110011 '
1+
b001010010001110110101111 ,
#1745
0+
#1750
b0000001111011100 #
b01001100 &
b00001101 '
1+
b001010011101110101101101 ,
#1755
0+
#1760
b0011011000100010 #
b01010010 &
b10101001 '
1+
b001010011110000101001001 ,
#1765
0+
#1770
b0000100010011000 #
b01101110 &
b00010100 '
1+
b001010100001011101101011 ,
#1775
0+
#1780
b1000011110100000 #
b10011011 &
b11100000 '
1+
b001010100010000000000011 ,
#1785
0+
#1790
b0011100010001100 #
b01001101 &
b10111100 '
1+
b001010101010011110100011 ,
#1795
0+
#1800
b0110100001001000 #
b10111100 &
b10001110 '
1+
b001010101110000000101111 ,
#1805
0+
#1810
b0011110111011010 #
b11001011 &
b01001110 '
1+
b001010110100100001110111 ,
#1815
0+
#1820
b0000001011100010 #
b01010010 &
b00001001 '
1+
b001010111000011001010001 ,
#1825
0+
#1830
b0000000000000000 #
b00000000 &
b01000101 '
1+
b001010111000100100110011 ,
#1835
0+
#1840
b1011110011110111 #
b11010111 &
b11100001 '
1+
#1845
0+
#1850
b0011110011011110 #
b10011111 &
b01100010 '
1+
b001011000100011000101010 ,
#1855
0+
#1860
b0011000000100010 #
b01100101 &
b01111010 '
1+
b001011001000001100001000 ,
#1865
0+
#1870
b1100000000101100 #
b11000100 &
b11111011 '
1+
b001011001011001100101010 ,
#1875
0+
#1880
b0011011011001001 #
b00110111 &
b11111111 '
1+
b001011010111001101010110 ,
#1885
0+
#1890
b0000000000101110 #
b00101110 &
b00000001 '
1+
b001011011010101000011111 ,
#1895
0+
#1900
b0111001101010100 #
b11110010 &
b01111010 '
1+
b001011011010101001001101 ,
#1905
0+
#1910
b0000001111111100 #
b00001111 &
b01000100 '
1+
b001011100001110110100001 ,
#1915
0+
#1920
b0001000100010111 #
b00100011 &
b01111101 '
1+
b001011100010000110011101 ,
#1925
0+
#1930
b0100001000001110 #
b01011001 &
b10111110 '
1+
b001011100011001010110100 ,
#1935
0+
#1940
b0011110011110100 #
b01011110 &
b10100110 '
1+
b001011100111010011000010 ,
#1945
0+
#1950
b0000110001111110 #
b01111011 &
b00011010 '
1+
b001011101011000110110110 ,
#1955
0+
#1960
b0000111000111000 #
b00110100 &
b01000110 '
1+
b001011101011111000110100 ,
#1965
0+
#1970
b0011011001110000 #
b01101000 &
b10000110 '
1+
b001011101100110001101100 ,
#1975
0+
#1980
b0010000011010000 #
b01010000 &
b01101001 '
1+
b001011110000001011011100 ,
#1985
0+
#1990
b0001111100010100 #
b11001100 &
b00100111 '
1+
b001011110010001110101100 ,
#1995
0+
#2000
b0001111011101110 #
b01001010 &
b01101011 '
1+
b001011110100001011000000 ,
#2005
0+
#2010
b0101111001010110 #
b10001010 &
b10101111 '
1+
b001011110110000110101110 ,
#2015
0+
#2020
b0100010111000110 #
b11100101 &
b01001110 '
1+
b001011111100000000000100 ,
#2025
0+
#2030
b0001001101000010 #
b10101010 &
b00011101 '
1+
b001100000000010111001010 ,
#2035
0+
#2040
b0100000101000101 #
b01001101 &
b11011001 '
1+
b001100000001100100001100 ,
#2045
0+
#2050
b0000011110000000 #
b00011110 &
b01000000 '
1+
b001100000101101001010001 ,
#2055
0+
#2060
b0000111010010111 #
b01010011 &
b00101101 '
1+
b001100000110000111010001 ,
#2065
0+
#2070
b0011110101011100 #
b10000100 &
b01110111 '
1+
b001100000111000001101000 ,
#2075
0+
#2080
b1001001110011111 #
b10101011 &
b11011101 '
1+
b001100001010110111000100 ,
#2085
0+
#2090
b0000000111011101 #
b00110101 &
b00001001 '
1+
b001100010100000101100011 ,
#2095
0+
#2100
b0101101000010000 #
b10000011 &
b10110000 '
1+
b001100010100001101000000 ,
#2105
0+
#2110
b0001100100000101 #
b00100011 &
b10110111 '
1+
b001100011001110101010000 ,
#2115
0+
#2120
b1000011100010100 #
b11110111 &
b10001100 '
1+
b001100011011011001010101 ,
#2125
0+
#2130
b0001000100110010 #
b00111110 &
b01000111 '
1+
b001100100011110101101001 ,
#2135
0+
#2140
b0000100110010010 #
b11110101 &
b00001010 '
1+
b001100100100111010011011 ,
#2145
0+
#2150
b0001101100010010 #
b01101110 &
b00111111 '
1+
b001100100101100000101101 ,
#2155
0+
#2160
b0111000101011000 #
b01110101 &
b11111000 '
1+
b001100100111001100111111 ,
#2165
0+
#2170
b0101001110101100 #
b11101110 &
b01011010 '
1+
b001100101110010010010111 ,
#2175
0+
#2180
b0010101001101111 #
b01000111 &
b10011001 '
1+
b001100110011100001000011 ,
#2185
0+
#2190
b0100010011001100 #
b01110111 &
b10010100 '
1+
b001100110110001010110010 ,
#2195
0+
#2200
b0100001011001100 #
b01110010 &
b10010110 '
1+
b001100111010011101111110 ,
#2205
0+
#2210
b1010001100100100 #
b11010100 &
b11000101 '
1+
b001100111110101001001010 ,
#2215
0+
#2220
b0100001111001011 #
b11000011 &
b01011001 '
1+
b001101001000110101101110 ,
#2225
0+
#2230
b0001100111001000 #
b00111100 &
b01101110 '
1+
b001101001101000100111001 ,
#2235
0+
#2240
b0001100000001100 #
b00110110 &
b01110010 '
1+
b001101001110101100000001 ,
#2245
0+
#2250
b0101011001110110 #
b01110111 &
b10111010 '
1+
b001101010000001100001101 ,
#2255
0+
#2260
b0001010010010110 #
b00100010 &
b10011011 '
1+
b001101010101100110000011 ,
#2265
0+
#2270
b0000101100001001 #
b01110001 &
b00011001 '
1+
b001101010110111000011001 ,
#2275
0+
#2280
b0001101010101001 #
b00100111 &
b10101111 '
1+
b001101010111100100100010 ,
#2285
0+
#2290
b0000101010000000 #
b01100000 &
b00011100 '
1+
b001101011001001111001011 ,
#2295
0+
#2300
b1001010110010111 #
b10111001 &
b11001111 '
1+
b001101011001111001001011 ,
#2305
0+
#2310
b0001000001011010 #
b01011011 &
b00101110 '
1+
b001101100011001111100010 ,
#2315
0+
#2320
b0011100010111111 #
b11000111 &
b01001001 '
1+
b001101100100010000111100 ,
#2325
0+
#2330
b0000011101111110 #
b10001001 &
b00001110 '
1+
b001101100111110011111011 ,
#2335
0+
#2340
b0000000000000000 #
b11100010 &
b00000000 '
1+
b001101101000010001111001 ,
#2345
0+
#2350
b0011010101111100 #
b10100011 &
b01010100 '
1+
#2355
0+
#2360
b0100010110111010 #
b10010110 &
b01110111 '
1+
b001101101011100111110101 ,
#2365
0+
#2370
b0000100100100100 #
b00011010 &
b01011010 '
1+
b001101101111111110101111 ,
#2375
0+
#2380
b0100010111100000 #
b11010000 &
b01010110 '
1+
b001101110000100011010011 ,
#2385
0+
#2390
b0000010101111000 #
b11001000 &
b00000111 '
1+
b001101110100111010110011 ,
#2395
0+
#2400
b0011001000000000 #
b01000000 '
1+
b001101110101010000101011 ,
#2405
0+
#2410
b1011000100101011 #
b11000001 &
b11101011 '
1+
b001101111000011000101011 ,
#2415
0+
#2420
b0010101011000110 #
b11011011 &
b00110010 '
1+
b001110000011011101010110 ,
#2425
0+
#2430
b0000000000001000 #
b00000100 &
b00000010 '
1+
b001110000110001000011100 ,
#2435
0+
#2440
b0101100100101010 #
b11100010 &
b01100101 '
1+
b001110000110001000100100 ,
#2445
0+
#2450
b0001001000101010 #
b00011110 &
b10011011 '
1+
b001110001011101101001110 ,
#2455
0+
#2460
b0001100010010100 #
b00110100 &
b01111001 '
1+
b001110001100110101111000 ,
#2465
0+
#2470
b1100011000001110 #
b11001010 &
b11111011 '
1+
b001110001110011000001100 ,
#2475
0+
#2480
b0011111011100110 #
b11000010 &
b01010011 '
1+
b001110011010110000011010 ,
#2485
0+
#2490
b0000011001110010 #
b00001010 &
b10100101 '
1+
b001110011110101100000000 ,
#2495
0+
#2500
b0011100000010111 #
b01010011 &
b10101101 '
1+
b001110011111000101110010 ,
#2505
0+
#2510
b1110001110011010 #
b11111001 &
b11101010 '
1+
b001110100010100110001001 ,
#2515
0+
#2520
b0000001010101100 #
b00100100 &
b00010011 '
1+
b001110110000110100100011 ,
#2525
0+
#2530
b0100000100010100 #
b01000100 &
b11110101 '
1+
b001110110000111111001111 ,
#2535
0+
#2540
b0000010011111000 #
b01101010 &
b00001100 '
1+
b001110110101000011100011 ,
#2545
0+
#2550
b0011000100111000 #
b11111100 &
b00110010 '
1+
b001110110101010111011011 ,
#2555
0+
#2560
b0011100000011100 #
b01001100 &
b10111101 '
1+
b001110111000011100010011 ,
#2565
0+
#2570
b0000010001101011 #
b00011101 &
b00100111 '
1+
b001110111011111100101111 ,
#2575
0+
#2580
b0001111110111110 #
b11101111 &
b00100010 '
1+
b001110111100001110011010 ,
#2585
0+
#2590
b0010000101111001 #
b00101001 &
b11010001 '
1+
b001110111110001101011000 ,
#2595
0+
#2600
b0010010101110001 #
b10000111 &
b01000111 '
1+
b001111000000010011010001 ,
#2605
0+
#2610
b0100111110011111 #
b01101101 &
b10111011 '
1+
b001111000010101001000010 ,
#2615
0+
#2620
b0010100101000000 #
b11000000 &
b00110111 '
1+
b001111000111100111100001 ,
#2625
0+
#2630
b0101110100100010 #
b10110110 &
b10000011 '
1+
b001111001010001100100001 ,
#2635
0+
#2640
b0110011110000000 #
b10001010 &
b11000000 '
1+
b001111010000000001000011 ,
#2645
0+
#2650
b0010001010001000 #
b00101000 &
b11011101 '
1+
b001111010110011111000011 ,
#2655
0+
#2660
b0000111000001101 #
b01101101 &
b00100001 '
1+
b001111011000101001001011 ,
#2665
0+
#2670
b0111000101111110 #
b11000111 &
b10010010 '
1+
b001111011001100001011000 ,
#2675
0+
#2680
b0000001001000111 #
b00110101 &
b00001011 '
1+
b001111100000100111010110 ,
#2685
0+
#2690
b0101001111011001 #
b10000111 &
b10011111 '
1+
b001111100000110000011101 ,
#2695
0+
#2700
b0000110001001000 #
b00011000 &
b10000011 '
1+
b001111100101111111110110 ,
#2705
0+
#2710
b0101000110100100 #
b11010001 &
b01100100 '
1+
b001111100110110000111110 ,
#2715
0+
#2720
b0011101111000000 #
b01000000 &
b11101111 '
1+
b001111101011110111100010 ,
#2725
0+
#2730
b0001100110110100 #
b10001100 &
b00101111 '
1+
b001111101111100110100010 ,
#2735
0+
#2740
b0000110000000101 #
b00010001 &
b10110101 '
1+
b001111110001001101010110 ,
#2745
0+
#2750
b0000000010011000 #
b00000001 &
b10011000 '
1+
b001111110001111101011011 ,
#2755
0+
#2760
b0110110010110110 #
b11111101 &
b01101110 '
1+
b001111110001111111110011 ,
#2765
0+
#2770
b0011110101000111 #
b01010011 &
b10111101 '
1+
b001111111000110010101001 ,
#2775
0+
#2780
b0000010111001101 #
b10100101 &
b00001001 '
1+
b001111111100100111110000 ,
#2785
0+
